{
    "vertices": [
        {
            "x": 6.290208670310676,
            "y": 4.440118553116918
        },
        {
            "x": 4.517446082085371,
            "y": 6.666520451195538
        },
        {
            "x": -2.822690175846219,
            "y": 9.697826755233109
        },
        {
            "x": 1.7893619472160935,
            "y": 6.9856199799105525
        },
        {
            "x": 1.817114512436092,
            "y": 2.4558447618037462
        },
        {
            "x": 5.616309656761587,
            "y": 5.214019225910306
        },
        {
            "x": 6.039005691323605,
            "y": 3.8397772600874305
        },
        {
            "x": 6.168056488037109,
            "y": 1.0518087157979608
        },
        {
            "x": 13.434224965050817,
            "y": 2.3365816744044423
        },
        {
            "x": 13.098180066794157,
            "y": 4.774860328994691
        },
        {
            "x": 12.32488312292844,
            "y": 5.45128632709384
        },
        {
            "x": 10.777448010630906,
            "y": 7.620047125034034
        },
        {
            "x": 8.17413978651166,
            "y": 9.565758219920099
        },
        {
            "x": 10.683863701298833,
            "y": 9.584530740045011
        },
        {
            "x": 12.38695262465626,
            "y": 9.483882574364543
        },
        {
            "x": 0.6240019015967846,
            "y": 10.948065737262368
        },
        {
            "x": 1.3986387345939875,
            "y": 10.494706583209336
        },
        {
            "x": 9.234867378138006,
            "y": 6.393287264741957
        },
        {
            "x": 11.016794135794044,
            "y": 4.0425484804436564
        },
        {
            "x": 8.464249089360237,
            "y": 3.4528319854289293
        }
    ]
}
