{
    "vertices": [
        {
            "x": 53.01268465351313,
            "y": -7.854467920027673
        },
        {
            "x": 56.57764923409559,
            "y": -6.881149151362479
        },
        {
            "x": 74.59013663115911,
            "y": -13.76329895388335
        },
        {
            "x": 61.98955839383416,
            "y": 10.544167974963784
        },
        {
            "x": 67.26151253795251,
            "y": 13.314318508841097
        },
        {
            "x": 57.96466552186757,
            "y": 26.90680838841945
        },
        {
            "x": 55.640665761893615,
            "y": 29.106479074805975
        },
        {
            "x": 57.819451176328585,
            "y": 28.431196206249297
        },
        {
            "x": 59.70668848603964,
            "y": 27.5095558417961
        },
        {
            "x": 66.01535527501255,
            "y": 19.46307599171996
        },
        {
            "x": 74.92827333393507,
            "y": 26.413764051161706
        },
        {
            "x": 73.52092835353687,
            "y": 39.86013034824282
        },
        {
            "x": 60.2633863943629,
            "y": 40.13782724365592
        },
        {
            "x": 68.17945270333439,
            "y": 34.295981489121914
        },
        {
            "x": 49.085423602955416,
            "y": 39.221365380100906
        },
        {
            "x": 26.441915058530867,
            "y": 42.25987940561026
        },
        {
            "x": 29.31101616472006,
            "y": 41.13518258463591
        },
        {
            "x": 42.796206946950406,
            "y": 35.03725899755955
        },
        {
            "x": 49.332532313419506,
            "y": 34.06374920532107
        },
        {
            "x": 43.27523934538476,
            "y": 34.78954767715186
        },
        {
            "x": 54.7116552607622,
            "y": 18.480411164462566
        },
        {
            "x": 53.41828284203075,
            "y": 12.54295470751822
        },
        {
            "x": 38.13436749042012,
            "y": 32.64503298513591
        },
        {
            "x": 35.81222613458522,
            "y": 35.47365991957486
        },
        {
            "x": 35.127875172765926,
            "y": 32.5640546483919
        },
        {
            "x": 39.31836689589545,
            "y": 22.377967529930174
        },
        {
            "x": 46.39226941508241,
            "y": 13.935031989589334
        },
        {
            "x": 44.54406856675632,
            "y": 9.266216024756432
        },
        {
            "x": 27.6318730332423,
            "y": 16.996709725819528
        },
        {
            "x": 38.60452884924598,
            "y": 1.8886129055172205
        },
        {
            "x": 38.306633464526385,
            "y": -1.2291805483400822
        },
        {
            "x": 28.22558001964353,
            "y": -16.16355368308723
        },
        {
            "x": 19.631065651774406,
            "y": -13.911682421341538
        },
        {
            "x": 14.706098714377731,
            "y": -18.05719179008156
        },
        {
            "x": 21.437654133187607,
            "y": -23.14543312881142
        },
        {
            "x": -9.018968035234138,
            "y": -17.281695912592113
        },
        {
            "x": -13.009681716794148,
            "y": -15.8391328221187
        },
        {
            "x": -1.1851902538910508,
            "y": -16.13669360615313
        },
        {
            "x": -23.218578023370355,
            "y": -12.594813482835889
        },
        {
            "x": -27.165808245772496,
            "y": 1.728417493402958
        },
        {
            "x": -32.13313570828177,
            "y": 5.939259206876159
        },
        {
            "x": -5.005408942233771,
            "y": -3.044482370838523
        },
        {
            "x": -6.139842005213723,
            "y": -3.1338655846193433
        },
        {
            "x": -10.10767653817311,
            "y": -3.9053216939792037
        },
        {
            "x": 13.029160819714889,
            "y": -2.380777733400464
        },
        {
            "x": 8.094005699967965,
            "y": -15.75244372151792
        },
        {
            "x": 14.406575071625412,
            "y": -10.10391282197088
        },
        {
            "x": 20.149533563526347,
            "y": -0.9641406266018748
        },
        {
            "x": 21.99365500244312,
            "y": 3.4711422119289637
        },
        {
            "x": 22.83394359285012,
            "y": 7.723946077749133
        },
        {
            "x": 19.912245153682306,
            "y": 11.714553469792008
        },
        {
            "x": 13.474357560044155,
            "y": 18.574860707856715
        },
        {
            "x": 39.70996636315249,
            "y": 16.727562316693366
        },
        {
            "x": 20.782063000369817,
            "y": 24.19167680852115
        },
        {
            "x": 35.88724555098452,
            "y": 28.3954363130033
        },
        {
            "x": 30.838076578220353,
            "y": 33.73267511744052
        },
        {
            "x": 28.64567777956836,
            "y": 34.63902114145458
        },
        {
            "x": 25.378953949548304,
            "y": 32.42068428825587
        },
        {
            "x": 15.96658238908276,
            "y": 41.26468959916383
        },
        {
            "x": 7.076104528969154,
            "y": 41.87651960272342
        },
        {
            "x": 1.2762152391951531,
            "y": 41.46528974082321
        },
        {
            "x": -33.940938140731305,
            "y": 39.52608598396182
        },
        {
            "x": -38.340390207013115,
            "y": 35.8808307107538
        },
        {
            "x": -57.673749182140455,
            "y": 35.411765959113836
        },
        {
            "x": -37.49489868641831,
            "y": 29.40832018852234
        },
        {
            "x": -27.225359394215047,
            "y": 31.12058541737497
        },
        {
            "x": -20.237120585516095,
            "y": 29.524370653554797
        },
        {
            "x": -10.387920860666782,
            "y": 28.878287920728326
        },
        {
            "x": -15.605716668069363,
            "y": 32.94075473677367
        },
        {
            "x": -17.01281866757199,
            "y": 35.06658395938575
        },
        {
            "x": 0.7104629371315241,
            "y": 33.75435625296086
        },
        {
            "x": 3.1362723524216563,
            "y": 25.440572751685977
        },
        {
            "x": 17.172112116822973,
            "y": 28.709341306239367
        },
        {
            "x": 6.095012800069526,
            "y": 24.152389707043767
        },
        {
            "x": 11.655874896096066,
            "y": 15.07177486922592
        },
        {
            "x": 6.550911554368213,
            "y": 15.096113154664636
        },
        {
            "x": -2.1705053618643433,
            "y": 16.884045864455402
        },
        {
            "x": -23.336878329282627,
            "y": 12.320720685645938
        },
        {
            "x": 4.02714297606226e-310,
            "y": 9.794394923374057
        },
        {
            "x": 1.829733420163393,
            "y": 6.256506672129035
        },
        {
            "x": -5.183427542215213,
            "y": 5.131115198135376
        },
        {
            "x": -30.74533891864121,
            "y": 7.166857343167067
        },
        {
            "x": -31.101978620281443,
            "y": 7.186536775901914
        },
        {
            "x": -35.219334340654314,
            "y": 14.35966169461608
        },
        {
            "x": -18.515712346415967,
            "y": 16.852556409314275
        },
        {
            "x": -19.21305358177051,
            "y": 21.520810236223042
        },
        {
            "x": -40.89496512198821,
            "y": 21.17760398890823
        },
        {
            "x": -43.07589365285821,
            "y": 19.750778677873313
        },
        {
            "x": -46.55819221632555,
            "y": 17.83425414469093
        },
        {
            "x": -61.038046893663704,
            "y": 22.897168640978634
        },
        {
            "x": -51.261174286482856,
            "y": 20.872931801714003
        },
        {
            "x": -76.58810810185969,
            "y": 26.727231772616506
        },
        {
            "x": -78.5593762435019,
            "y": 21.636653498746455
        },
        {
            "x": -62.44875598233193,
            "y": 12.655765981413424
        },
        {
            "x": -68.92767317011021,
            "y": 9.865609993226826
        },
        {
            "x": -54.454334165202454,
            "y": 10.733602808788419
        },
        {
            "x": -58.753622436197475,
            "y": 6.645261669531465
        },
        {
            "x": -72.9122862929944,
            "y": 5.5443651443347335
        },
        {
            "x": -75.26574922841974,
            "y": 11.420097599737346
        },
        {
            "x": -75.40656292811036,
            "y": -1.1356445541605353
        },
        {
            "x": -73.62528883153573,
            "y": -2.18378593493253
        },
        {
            "x": -66.39023431227542,
            "y": -7.436849781312048
        },
        {
            "x": -75.57602101704106,
            "y": -3.464572763070464
        },
        {
            "x": -76.12758442293853,
            "y": -29.92988138180226
        },
        {
            "x": -69.14138531894423,
            "y": -28.824764396995306
        },
        {
            "x": -57.18533044564538,
            "y": -21.591764520853758
        },
        {
            "x": -69.50165095855482,
            "y": -24.34196122083813
        },
        {
            "x": -70.25630898890086,
            "y": -16.85557125788182
        },
        {
            "x": -47.83628976903856,
            "y": 2.1455226317048073
        },
        {
            "x": -37.9473609442357,
            "y": 2.9493008106946945
        },
        {
            "x": -29.63975310791284,
            "y": -0.01877849828451872
        },
        {
            "x": -55.22554503986612,
            "y": -16.87272016890347
        },
        {
            "x": -47.83995472476818,
            "y": -13.131765729747713
        },
        {
            "x": -40.66644067293964,
            "y": -12.246412916108966
        },
        {
            "x": -40.36682593985461,
            "y": -19.44578179065138
        },
        {
            "x": -51.77996695507318,
            "y": -23.066207363270223
        },
        {
            "x": -54.52933957334608,
            "y": -27.491279451176524
        },
        {
            "x": -34.19776227325201,
            "y": -18.06192637141794
        },
        {
            "x": -58.077106196433306,
            "y": -32.92884071264416
        },
        {
            "x": -65.73707790230401,
            "y": -38.17475050594658
        },
        {
            "x": -20.454485808731988,
            "y": -30.265698300674558
        },
        {
            "x": -11.184032839955762,
            "y": -29.647022164426744
        },
        {
            "x": -19.192796910647303,
            "y": -18.67114832252264
        },
        {
            "x": 2.4508142983540893,
            "y": -26.65661095827818
        },
        {
            "x": -7.305678497068584,
            "y": -17.934320461936295
        },
        {
            "x": 9.100197436055169,
            "y": -25.11426304001361
        },
        {
            "x": 3.6296291823964566,
            "y": -32.39156292472035
        },
        {
            "x": 7.749136600177735,
            "y": -35.023135187104344
        },
        {
            "x": -8.338978041429073,
            "y": -31.932251107878983
        },
        {
            "x": -65.86599243222736,
            "y": -38.34413146879524
        },
        {
            "x": -74.59284880547784,
            "y": -42.294748215936124
        },
        {
            "x": -32.41974454605952,
            "y": -37.586622883565724
        },
        {
            "x": -20.14387100120075,
            "y": -37.49396031163633
        },
        {
            "x": -2.4558571237139404,
            "y": -37.85933394357562
        },
        {
            "x": -27.29377725510858,
            "y": -42.775331809185445
        },
        {
            "x": 34.180597466183826,
            "y": -41.991310553625226
        },
        {
            "x": 45.08207029430196,
            "y": -41.93770457338542
        },
        {
            "x": 48.015741758281365,
            "y": -39.27280486468226
        },
        {
            "x": 40.230547467945144,
            "y": -38.717641143128276
        },
        {
            "x": 21.78991269785911,
            "y": -42.02562395390123
        },
        {
            "x": 17.301439926959574,
            "y": -37.45206579845399
        },
        {
            "x": 13.687125875148922,
            "y": -36.647458168677986
        },
        {
            "x": 3.459814506350085,
            "y": -41.85635608341545
        },
        {
            "x": 12.335044343490154,
            "y": -34.60973094031215
        },
        {
            "x": 31.780647144187242,
            "y": -27.445157430134714
        },
        {
            "x": 42.18684760504402,
            "y": -32.89818547386676
        },
        {
            "x": 50.59530036058277,
            "y": -40.00821262318641
        },
        {
            "x": 45.09680587914772,
            "y": -29.92472266405821
        },
        {
            "x": 41.81671494618058,
            "y": -26.906933134421706
        },
        {
            "x": 28.63483076915145,
            "y": -21.200690609402955
        },
        {
            "x": 32.73995310184546,
            "y": -19.159444662742317
        },
        {
            "x": 37.05152375274338,
            "y": -12.988403419032693
        },
        {
            "x": 51.588207063032314,
            "y": -17.144110523164272
        },
        {
            "x": 49.04895314597525,
            "y": -18.8943385835737
        },
        {
            "x": 56.703905349131674,
            "y": -24.92791806254536
        },
        {
            "x": 57.42104971082881,
            "y": -22.812409759499133
        },
        {
            "x": 67.80801801010966,
            "y": -33.145652908831835
        },
        {
            "x": 67.7560632233508,
            "y": -37.76049394160509
        },
        {
            "x": 64.62212841608562,
            "y": -40.34349291399121
        },
        {
            "x": 67.46634557959624,
            "y": -40.59719300363213
        },
        {
            "x": 77.65313678537495,
            "y": -15.814440282061696
        },
        {
            "x": 77.50986577360891,
            "y": -4.0787986908108
        },
        {
            "x": 77.32226816704497,
            "y": 0.9805685738101602
        },
        {
            "x": 75.32655789284036,
            "y": 6.621069154702127
        },
        {
            "x": 72.05578479683027,
            "y": 22.236919247545302
        },
        {
            "x": 71.60815414041281,
            "y": 13.332738627679646
        },
        {
            "x": 75.209517669864,
            "y": -11.398079950362444
        },
        {
            "x": 77.02128194505349,
            "y": -15.105956475250423
        },
        {
            "x": 70.2107023622375,
            "y": -28.82452219352126
        },
        {
            "x": 59.574581247288734,
            "y": -12.42979602701962
        },
        {
            "x": 48.15150544513017,
            "y": -10.244899472221732
        },
        {
            "x": 43.03404065198265,
            "y": -4.451850108802319
        },
        {
            "x": 44.59704111563042,
            "y": 0.20549643225967884
        },
        {
            "x": 50.89668174739927,
            "y": -2.49733002576977
        },
        {
            "x": 53.34302535862662,
            "y": -2.5587583212181926
        }
    ]
}
