{
    "vertices": [
        {
            "x": -7.710514445789158,
            "y": -11.664205390959978
        },
        {
            "x": 9.877429387997836,
            "y": -9.970016956329346
        },
        {
            "x": 12.081397748552263,
            "y": -6.759886287152767
        },
        {
            "x": 12.556144678965211,
            "y": -11.561060160398483
        },
        {
            "x": 14.287478558253497,
            "y": -11.568005070090294
        },
        {
            "x": 16.005036381538957,
            "y": -2.91291294246912
        },
        {
            "x": 13.687333641573787,
            "y": -3.2118527367711067
        },
        {
            "x": 19.315465099643916,
            "y": 1.0813867561519146
        },
        {
            "x": 19.244014718569815,
            "y": 3.6908252723515034
        },
        {
            "x": 11.265698131173849,
            "y": 6.979852080345154
        },
        {
            "x": 5.921379590872675,
            "y": 7.581368330866098
        },
        {
            "x": -10.128583791665733,
            "y": 11.315564196556807
        },
        {
            "x": -14.645443176850677,
            "y": 5.20148641616106
        },
        {
            "x": -15.749760617036372,
            "y": 3.3071254938840866
        },
        {
            "x": -21.84990558307618,
            "y": 2.1477903462946415
        },
        {
            "x": -11.897325098980218,
            "y": 0.9378681443631649
        },
        {
            "x": -10.079457499086857,
            "y": 2.450164195150137
        },
        {
            "x": -9.731460241600871,
            "y": 3.494635507464409
        },
        {
            "x": -3.4828020120039582,
            "y": 3.474796324968338
        },
        {
            "x": -3.715497285593301,
            "y": 3.985048670321703
        },
        {
            "x": -5.432500604074448,
            "y": 8.034110683947802
        },
        {
            "x": 0.7061981409788132,
            "y": 7.325977049767971
        },
        {
            "x": 4.2822902533225715,
            "y": 7.254817184060812
        },
        {
            "x": 11.607021822128445,
            "y": 3.9197382889688015
        },
        {
            "x": 12.088726088404655,
            "y": 1.1370871625840664
        },
        {
            "x": 13.54154015891254,
            "y": 0.5681723915040493
        },
        {
            "x": 8.245784270111471,
            "y": 2.0643591172993183
        },
        {
            "x": 0.12820510659366846,
            "y": 4.293073620647192
        },
        {
            "x": 5.436849009711295,
            "y": -0.7891760431230068
        },
        {
            "x": 9.430633275769651,
            "y": -1.0322791635990143
        },
        {
            "x": 12.775896491948515,
            "y": -5.7960468493402
        },
        {
            "x": 13.605736547615379,
            "y": -6.839857533574104
        },
        {
            "x": 14.15765413083136,
            "y": -10.742868885397911
        },
        {
            "x": 9.894556298386306,
            "y": -2.3618531338870525
        },
        {
            "x": 5.92876851093024,
            "y": -3.7788729071617126
        },
        {
            "x": 4.86447136849165,
            "y": -6.1972400061786175
        },
        {
            "x": -1.09924928420515e-310,
            "y": -1.9459338001906872
        },
        {
            "x": -2.2528552869334817,
            "y": -1.135947234928608
        },
        {
            "x": -2.6977971545420587,
            "y": 3.9707034565508366
        },
        {
            "x": -3.1676686042919755,
            "y": 1.9267099611461163
        },
        {
            "x": -2.7297890139743686,
            "y": -1.1533787325024605
        },
        {
            "x": -12.282769912853837,
            "y": -3.50132804363966
        },
        {
            "x": -20.7933074911125,
            "y": -4.78034408390522
        },
        {
            "x": -11.647465594578534,
            "y": -9.951877422630787
        },
        {
            "x": -9.704939061775804,
            "y": -8.67821005359292
        },
        {
            "x": -6.529759622644633,
            "y": -7.298072956502438
        },
        {
            "x": -11.149967748206109,
            "y": -5.867590315639973
        },
        {
            "x": 4.351031917613,
            "y": -8.770891137421131
        },
        {
            "x": 9.866652628406882,
            "y": -8.466282058507204
        },
        {
            "x": 3.164395575877279,
            "y": -9.327721327543259
        }
    ]
}
